[
  {
    "id": "aurora-mayor",
    "municipality": "Aurora",
    "office": "Mayor",
    "ward": null,
    "seat_label": "Mayor",
    "is_regional_seat": true,
    "incumbent_candidate_id": "aurora-mayor-tom-mrakas",
    "source": "manual_seed",
    "notes": "Mayor represents this municipality on York Regional Council."
  },
  {
    "id": "east-gwillimbury-mayor",
    "municipality": "East Gwillimbury",
    "office": "Mayor",
    "ward": null,
    "seat_label": "Mayor",
    "is_regional_seat": true,
    "incumbent_candidate_id": "east-gwillimbury-mayor-virginia-hackson",
    "source": "manual_seed",
    "notes": "Mayor represents this municipality on York Regional Council."
  },
  {
    "id": "georgina-mayor",
    "municipality": "Georgina",
    "office": "Mayor",
    "ward": null,
    "seat_label": "Mayor",
    "is_regional_seat": true,
    "incumbent_candidate_id": "georgina-mayor-margaret-quirk",
    "source": "manual_seed",
    "notes": ""
  },
  {
    "id": "georgina-regional-councillor-1",
    "municipality": "Georgina",
    "office": "Regional Councillor",
    "ward": null,
    "seat_label": "Regional Councillor (at-large seat 1 of 1)",
    "is_regional_seat": true,
    "incumbent_candidate_id": "georgina-regional-councillor-1-naomi-davison",
    "source": "manual_seed",
    "notes": "At-large regional councillor seat; not tied to a specific numbered ward."
  },
  {
    "id": "king-mayor",
    "municipality": "King",
    "office": "Mayor",
    "ward": null,
    "seat_label": "Mayor",
    "is_regional_seat": true,
    "incumbent_candidate_id": "king-mayor-steve-pellegrini",
    "source": "manual_seed",
    "notes": "Mayor represents this municipality on York Regional Council."
  },
  {
    "id": "markham-mayor",
    "municipality": "Markham",
    "office": "Mayor",
    "ward": null,
    "seat_label": "Mayor",
    "is_regional_seat": true,
    "incumbent_candidate_id": "markham-mayor-frank-scarpitti",
    "source": "manual_seed",
    "notes": ""
  },
  {
    "id": "markham-regional-councillor-1",
    "municipality": "Markham",
    "office": "Regional Councillor",
    "ward": null,
    "seat_label": "Regional Councillor (at-large seat 1 of 4)",
    "is_regional_seat": true,
    "incumbent_candidate_id": "markham-regional-councillor-1-michael-chan",
    "source": "manual_seed",
    "notes": "At-large regional councillor seat; not tied to a specific numbered ward."
  },
  {
    "id": "markham-regional-councillor-2",
    "municipality": "Markham",
    "office": "Regional Councillor",
    "ward": null,
    "seat_label": "Regional Councillor (at-large seat 2 of 4)",
    "is_regional_seat": true,
    "incumbent_candidate_id": "markham-regional-councillor-2-jim-jones",
    "source": "manual_seed",
    "notes": "At-large regional councillor seat; not tied to a specific numbered ward."
  },
  {
    "id": "markham-regional-councillor-3",
    "municipality": "Markham",
    "office": "Regional Councillor",
    "ward": null,
    "seat_label": "Regional Councillor (at-large seat 3 of 4)",
    "is_regional_seat": true,
    "incumbent_candidate_id": "markham-regional-councillor-3-joe-li",
    "source": "manual_seed",
    "notes": "At-large regional councillor seat; not tied to a specific numbered ward."
  },
  {
    "id": "markham-regional-councillor-4",
    "municipality": "Markham",
    "office": "Regional Councillor",
    "ward": null,
    "seat_label": "Regional Councillor (at-large seat 4 of 4)",
    "is_regional_seat": true,
    "incumbent_candidate_id": "markham-regional-councillor-4-alan-ho",
    "source": "manual_seed",
    "notes": "At-large regional councillor seat; not tied to a specific numbered ward."
  },
  {
    "id": "newmarket-mayor",
    "municipality": "Newmarket",
    "office": "Mayor",
    "ward": null,
    "seat_label": "Mayor",
    "is_regional_seat": true,
    "incumbent_candidate_id": "newmarket-mayor-john-taylor",
    "source": "manual_seed",
    "notes": ""
  },
  {
    "id": "newmarket-regional-councillor-1",
    "municipality": "Newmarket",
    "office": "Regional Councillor",
    "ward": null,
    "seat_label": "Regional Councillor (at-large seat 1 of 1)",
    "is_regional_seat": true,
    "incumbent_candidate_id": "newmarket-regional-councillor-1-tom-vegh",
    "source": "manual_seed",
    "notes": "At-large regional councillor seat; not tied to a specific numbered ward."
  },
  {
    "id": "richmond-hill-mayor",
    "municipality": "Richmond Hill",
    "office": "Mayor",
    "ward": null,
    "seat_label": "Mayor",
    "is_regional_seat": true,
    "incumbent_candidate_id": "richmond-hill-mayor-david-west",
    "source": "manual_seed",
    "notes": ""
  },
  {
    "id": "richmond-hill-regional-councillor-1",
    "municipality": "Richmond Hill",
    "office": "Regional Councillor",
    "ward": null,
    "seat_label": "Regional Councillor (at-large seat 1 of 2)",
    "is_regional_seat": true,
    "incumbent_candidate_id": "richmond-hill-regional-councillor-1-godwin-chan",
    "source": "manual_seed",
    "notes": "At-large regional councillor seat; not tied to a specific numbered ward."
  },
  {
    "id": "richmond-hill-regional-councillor-2",
    "municipality": "Richmond Hill",
    "office": "Regional Councillor",
    "ward": null,
    "seat_label": "Regional Councillor (at-large seat 2 of 2)",
    "is_regional_seat": true,
    "incumbent_candidate_id": "richmond-hill-regional-councillor-2-joe-dipaola",
    "source": "manual_seed",
    "notes": "At-large regional councillor seat; not tied to a specific numbered ward."
  },
  {
    "id": "vaughan-mayor",
    "municipality": "Vaughan",
    "office": "Mayor",
    "ward": null,
    "seat_label": "Mayor",
    "is_regional_seat": true,
    "incumbent_candidate_id": "vaughan-mayor-steven-del-duca",
    "source": "manual_seed",
    "notes": ""
  },
  {
    "id": "vaughan-regional-councillor-1",
    "municipality": "Vaughan",
    "office": "Regional Councillor",
    "ward": null,
    "seat_label": "Regional Councillor (at-large seat 1 of 4)",
    "is_regional_seat": true,
    "incumbent_candidate_id": "vaughan-regional-councillor-1-linda-d-jackson",
    "source": "manual_seed",
    "notes": "At-large regional councillor seat; not tied to a specific numbered ward."
  },
  {
    "id": "vaughan-regional-councillor-2",
    "municipality": "Vaughan",
    "office": "Regional Councillor",
    "ward": null,
    "seat_label": "Regional Councillor (at-large seat 2 of 4)",
    "is_regional_seat": true,
    "incumbent_candidate_id": "vaughan-regional-councillor-2-mario-ferri",
    "source": "manual_seed",
    "notes": "At-large regional councillor seat; not tied to a specific numbered ward."
  },
  {
    "id": "vaughan-regional-councillor-3",
    "municipality": "Vaughan",
    "office": "Regional Councillor",
    "ward": null,
    "seat_label": "Regional Councillor (at-large seat 3 of 4)",
    "is_regional_seat": true,
    "incumbent_candidate_id": "vaughan-regional-councillor-3-gino-rosati",
    "source": "manual_seed",
    "notes": "At-large regional councillor seat; not tied to a specific numbered ward."
  },
  {
    "id": "vaughan-regional-councillor-4",
    "municipality": "Vaughan",
    "office": "Regional Councillor",
    "ward": null,
    "seat_label": "Regional Councillor (at-large seat 4 of 4)",
    "is_regional_seat": true,
    "incumbent_candidate_id": "vaughan-regional-councillor-4-mario-g-racco",
    "source": "manual_seed",
    "notes": "At-large regional councillor seat; not tied to a specific numbered ward."
  },
  {
    "id": "whitchurch-stouffville-mayor",
    "municipality": "Whitchurch-Stouffville",
    "office": "Mayor",
    "ward": null,
    "seat_label": "Mayor",
    "is_regional_seat": true,
    "incumbent_candidate_id": "whitchurch-stouffville-mayor-iain-lovatt",
    "source": "manual_seed",
    "notes": "Mayor represents this municipality on York Regional Council."
  }
]
